logkontrol/__init__.py
logkontrol/logkontrol.py
logkontrol-0.2.2.dist-info/LICENSE
logkontrol-0.2.2.dist-info/LICENSE_PYYAML.txt
logkontrol-0.2.2.dist-info/METADATA
logkontrol-0.2.2.dist-info/WHEEL
logkontrol-0.2.2.dist-info/top_level.txt
logkontrol-0.2.2.dist-info/RECORD
