Metadata-Version: 2.1
Name: logkontrol
Version: 0.2.2
Summary: Custom file logging system for Python applications
Author-email: voidfemme <rosemkatt@gmail.com>
License: CC0 1.0 Universal (CC0 1.0) Public Domain Dedication
Project-URL: Homepage, https://github.com/voidfemme/logkontrol
Project-URL: Bug_Tracker, https://github.com/voidfemme/logkontrol/issues
Classifier: Programming Language :: Python :: 3
Classifier: Operating System :: OS Independent
Requires-Python: >=3.6
License-File: LICENSE
License-File: LICENSE_PYYAML.txt
Requires-Dist: PyYAML
